console_snake-1.0.0.dist-info/DESCRIPTION.rst
console_snake-1.0.0.dist-info/METADATA
console_snake-1.0.0.dist-info/RECORD
console_snake-1.0.0.dist-info/WHEEL
console_snake-1.0.0.dist-info/entry_points.txt
console_snake-1.0.0.dist-info/metadata.json
console_snake-1.0.0.dist-info/top_level.txt
snake/constants.py
snake/snake.py
