Metadata-Version: 2.0
Name: console-snake
Version: 1.0.0
Summary: Snake for console
Home-page: https://github.com/chunkhang/console-snake
Author: Marcus Mu
Author-email: chunkhang@gmail.com
License: UNLICENSE
Keywords: snake,console,curses
Platform: UNKNOWN
Classifier: Intended Audience :: End Users/Desktop
Classifier: Environment :: Console
Classifier: Programming Language :: Python :: 3 :: Only
Requires-Python: >=3
